snakemq_pubsub/__init__.py
snakeMQ_PubSub-0.1.0.dist-info/DESCRIPTION.rst
snakeMQ_PubSub-0.1.0.dist-info/METADATA
snakeMQ_PubSub-0.1.0.dist-info/metadata.json
snakeMQ_PubSub-0.1.0.dist-info/RECORD
snakeMQ_PubSub-0.1.0.dist-info/top_level.txt
snakeMQ_PubSub-0.1.0.dist-info/WHEEL
