Metadata-Version: 2.0
Name: snakeMQ-PubSub
Version: 0.1.0
Summary: An implementation of the publish-subscribe pattern for snakeMQ.
Home-page: https://github.com/repole/snakemq-pubsub
Author: Nicholas Repole
Author-email: n.repole@gmail.com
License: MIT
Download-URL: https://github.com/repole/snakemq-pubsub/tarball/0.1.0
Keywords: snakeMQ,pubsub
Platform: any
Classifier: Development Status :: 3 - Alpha
Classifier: Intended Audience :: Developers
Classifier: License :: OSI Approved :: MIT License
Classifier: Programming Language :: Python
Classifier: Programming Language :: Python :: 2
Classifier: Programming Language :: Python :: 2.7
Classifier: Programming Language :: Python :: 3
Classifier: Programming Language :: Python :: 3.3
Classifier: Programming Language :: Python :: 3.4
Classifier: Programming Language :: Python :: Implementation :: CPython
Classifier: Programming Language :: Python :: Implementation :: PyPy
Classifier: Operating System :: OS Independent
Requires-Dist: snakeMQ (>=1.2)
